{
  "children": [
    {
      "path": "about",
      "text": "About",
      "visible": false
    },     
    {
      "path": "index.json",
      "text": "Index.json",
      "visible": false
    },
    {
      "path": "index",
      "text": "Index",
      "visible": false
    },
    {
      "path": "instructions",
      "children": [
        {
          "path": "instructions/index",
          "text": "Index",
          "visible": false
        }
      ],
      "text": "Instructions",
      "visible": false
    },
    {
      "path": "why-use-orangesys",
      "text": "Why use Orangesys?",
      "visible": true,
      "children": [
        {
          "path": "why-use-orangesys",
          "text": "Why use Orangesys",
          "visible": true
        },
        {
          "path": "why-use-orangesys/pricing",
          "text": "Pricing",
          "visible": true,
          "children": [
            {
              "path": "index",
              "text": "index",
              "visible": false
            }
          ]
        },
        {
          "path": "why-use-orangesys/use-cases",
          "children": [
            {
              "path": "index",
              "text": "Index",
              "visible": false
            },
            {
              "path": "why-use-orangesys/use-cases/create-responsive-website",
              "text": "Create a responsive website",
              "visible": false
            },
            {
              "path": "why-use-orangesys/use-cases/resolve-incompatibilities-after-upgrade",
              "text": "Resolve incompatibilities",
              "visible": false
            },
            {
              "path": "why-use-orangesys/use-cases/refactor-monolithic-to-microsystems",
              "text": "Refactor to microservices",
              "visible": false
            }
            ],
          "text": "Use cases",
          "visible": false
        }
      ]
    },
    {
      "path": "documentation/how-orangesys-works/architecture-and-components",
      "children": [
        {
          "path": "documentation/how-orangesys-works/architecture-and-components",
          "children": [
            {
              "path": "documentation/how-orangesys-works/architecture-and-components",
              "text": "Architecture and components",
              "visible": false
            },
            {
              "path": "documentation/how-orangesys-works/requirements",
              "text": "Requirements",
              "visible": false
            }
          ],
          "text": "How Orangesys works",
          "visible": false
        },
        {
          "path": "documentation/installation",
          "children":
          [
            {
              "path": "documentation/installation",
              "text": "Overview",
              "visible": true
            },
            {
              "path": "documentation/installation/ubuntu-debian",
              "text": "Ubuntu & Debian",
              "visible": true
            },
            {
              "path": "documentation/installation/redhat-centos",
              "text": "Redhat & Centos & Amazon Linux",
              "visible": true
            }
          ],
          "text": "Installation",
          "visible": true
        },
        {
          "path": "documentation/terms-of-use",
          "children":
          [
            {
              "path": "index",
              "text": "Index",
              "visible": false
            },
            {
              "path": "documentation/terms-of-use/law",
              "text": "特定商取引に関する表記",
              "visible": true
            },
            {
              "path": "documentation/terms-of-use/privacy",
              "text": "プライバシーポリシー",
              "visible": true
            }
          ],
          "text": "Terms of Use",
          "visible": true
        },
        {
          "path": "documentation/using-grafana/artifacts",
          "children": [
            {
              "path": "documentation/using-grafana/artifacts",
              "text": "Artifacts",
              "visible": false
            }
          ],
          "text": "Using grafana",
          "visible": false
        }
        ],
      "text": "Documentation",
      "visible": true
    },
    {
      "path": "support",
      "text": "Support",
      "visible": true
    }
  ]
}
